ankiconverters/angielski2anki.py
ankiconverters/angielski_word.py
ankiconverters/wiersze2anki.py
ankiconverters-0.1.1.dist-info/METADATA
ankiconverters-0.1.1.dist-info/WHEEL
ankiconverters-0.1.1.dist-info/entry_points.txt
ankiconverters-0.1.1.dist-info/RECORD
